aiohttp_test_utils/__init__.py
aiohttp_test_utils-0.5.0.dist-info/METADATA
aiohttp_test_utils-0.5.0.dist-info/WHEEL
aiohttp_test_utils-0.5.0.dist-info/top_level.txt
aiohttp_test_utils-0.5.0.dist-info/zip-safe
aiohttp_test_utils-0.5.0.dist-info/RECORD
