Metadata-Version: 2.1
Name: aiohttp-test-utils
Version: 0.5.0
Summary: a small library used for testing aiohttp projects
Author-email: 5j9 <5j9@users.noreply.github.com>
License: GNU General Public License v3 (GPLv3)
Project-URL: Homepage, https://github.com/5j9/aiohttp_test_utils
Classifier: License :: OSI Approved :: GNU General Public License v3 (GPLv3)
Classifier: Programming Language :: Python :: 3.10
Requires-Python: >=3.10
Requires-Dist: pytest
Requires-Dist: pytest-asyncio
Requires-Dist: python-decouple
